{"assets":{"D92B21197D6964D0B82B3A219F1FA856":{"type":"texture","index":1,"assetRequest":{"type":"slide","state":"contents","slide":"none"},"url":{"native":"assets\/9FED2E06-2ECE-4085-A522-B2B5EA8C1361.pdf"},"width":1920,"height":1080},"C054A79B4EE8BE1C7852CE41F3B9DE1D":{"type":"texture","index":0,"assetRequest":{"type":"slide","state":"contents","slide":"none"},"url":{"native":"assets\/9FED2E06-2ECE-4085-A522-B2B5EA8C1361.pdf"},"width":1920,"height":1080}},"events":[{"effects":[{"beginTime":0.10000000149011612,"baseLayer":{"animations":[],"initialState":{"affineTransform":[1,0,0,1,0,0],"masksToBounds":false,"rotation":0,"scale":1,"position":{"pointX":960,"pointY":540},"width":1920,"sublayerTransform":[1,0,0,0,0,1,0,0,0,0,1,0,0,0,0,1],"contentsRect":{"y":0,"x":0,"width":1,"height":1},"opacity":1,"edgeAntialiasingMask":251658240,"height":1080,"hidden":false,"anchorPoint":{"pointX":0.5,"pointY":0.5}},"objectID":"0","layers":[{"animations":[],"initialState":{"affineTransform":[1,0,0,1,0,0],"masksToBounds":false,"rotation":0,"scale":1,"position":{"pointX":960,"pointY":540},"width":1920,"sublayerTransform":[1,0,0,0,0,1,0,0,0,0,1,-0.00035007912466775983,0,0,0,1],"contentsRect":{"y":0,"x":0,"width":1,"height":1},"opacity":1,"edgeAntialiasingMask":251658240,"height":1080,"hidden":false,"anchorPoint":{"pointX":0.5,"pointY":0.5}},"layers":[{"animations":[],"layers":[],"texturedRectangle":{"isBackgroundTexture":false,"singleTextureOpacity":1,"textureType":0,"textBaseline":0,"textXHeight":0,"isVerticalText":false},"initialState":{"affineTransform":[1,0,0,1,0,0],"masksToBounds":false,"rotation":0,"scale":1,"position":{"pointX":960,"pointY":540},"width":1920,"sublayerTransform":[1,0,0,0,0,1,0,0,0,0,1,0,0,0,0,1],"contentsRect":{"y":0,"x":0,"width":1,"height":1},"opacity":1,"edgeAntialiasingMask":0,"height":1080,"hidden":false,"anchorPoint":{"pointX":0.5,"pointY":0.5}},"texture":"D92B21197D6964D0B82B3A219F1FA856"},{"animations":[{"repeatCount":0,"removedOnCompletion":false,"from":{"scalar":1},"timingFunction":"EaseInEaseOut","additive":false,"timeOffset":0,"autoreverses":false,"property":"opacity","fillMode":"both","duration":0.5,"beginTime":0,"to":{"scalar":0}}],"layers":[],"texturedRectangle":{"isBackgroundTexture":false,"singleTextureOpacity":1,"textureType":0,"textBaseline":0,"textXHeight":0,"isVerticalText":false},"initialState":{"affineTransform":[1,0,0,1,0,0],"masksToBounds":false,"rotation":0,"scale":1,"position":{"pointX":960,"pointY":540},"width":1920,"sublayerTransform":[1,0,0,0,0,1,0,0,0,0,1,0,0,0,0,1],"contentsRect":{"y":0,"x":0,"width":1,"height":1},"opacity":1,"edgeAntialiasingMask":0,"height":1080,"hidden":false,"anchorPoint":{"pointX":0.5,"pointY":0.5}},"texture":"C054A79B4EE8BE1C7852CE41F3B9DE1D"}]}]},"effects":[],"duration":0.5,"type":"transition","attributes":{"direction":0},"name":"apple:dissolve","objectID":"0"}],"automaticPlay":true,"hyperlinks":[],"accessibility":[{"text":"Realization","targetRectangle":{"y":45.879440009593964,"x":62.879581451416016,"width":158.78999999999999,"height":40.612979987377912}},{"text":"Exit","targetRectangle":{"y":844.4735107421875,"x":898.82428307408099,"width":53.311999999999898,"height":37.10400390625}},{"text":"Events","targetRectangle":{"y":537.38702392578125,"x":546.6782627604008,"width":96.607999999999947,"height":37.10400390625}},{"text":"camera, objects, lights CRUD","targetRectangle":{"y":518.63702392578125,"x":806.34562841796878,"width":247.16800000000012,"height":75.10400390625}},{"text":"function render() {","targetRectangle":{"y":336.715665102005,"x":1236.93701171875,"width":320.291015625,"height":33}},{"text":"  renderer.render();","targetRectangle":{"y":369.715665102005,"x":1236.93701171875,"width":337.1484375,"height":33}},{"text":"}","targetRectangle":{"y":402.715665102005,"x":1236.93701171875,"width":16.857421875,"height":33}},{"text":"Create renderer","targetRectangle":{"y":383.84378051757812,"x":814.05628307408097,"width":222.84799999999996,"height":37.10400390625}},{"text":"Render","targetRectangle":{"y":690.93023681640625,"x":873.62428307408095,"width":103.71199999999999,"height":37.10400390625}},{"text":"function update() {","targetRectangle":{"y":457.1059582233429,"x":1236.93701171875,"width":320.291015625,"height":33}},{"text":"  obj.update();","targetRectangle":{"y":490.1059582233429,"x":1236.93701171875,"width":252.861328125,"height":33}},{"text":"  \/\/ ...","targetRectangle":{"y":523.1059582233429,"x":1236.93701171875,"width":134.859375,"height":33}},{"text":"}","targetRectangle":{"y":556.1059582233429,"x":1236.93701171875,"width":16.857421875,"height":33}},{"text":"function destroy() {","targetRectangle":{"y":797.17730832099915,"x":1236.93701171875,"width":337.1484375,"height":33}},{"text":"  obj.dispose();","targetRectangle":{"y":830.17730832099915,"x":1236.93701171875,"width":269.71875,"height":33}},{"text":"  \/\/ ...","targetRectangle":{"y":863.17730832099915,"x":1236.93701171875,"width":134.859375,"height":33}},{"text":"}","targetRectangle":{"y":896.17730832099915,"x":1236.93701171875,"width":16.857421875,"height":33}},{"text":"let scene, camera, obj, light, renderer;","targetRectangle":{"y":29.935058772563934,"x":1236.9371337890625,"width":674.296875,"height":33}},{"text":"Create camera, objects, lights","targetRectangle":{"y":211.55052185058594,"x":815.83362841796873,"width":228.19199999999989,"height":75.10400390625}},{"text":"function init() {","targetRectangle":{"y":84.325357913970947,"x":1236.93701171875,"width":286.576171875,"height":33}},{"text":"  scene = new Scene();","targetRectangle":{"y":117.32535791397095,"x":1236.93701171875,"width":370.86328125,"height":33}},{"text":"  camera = new PerspectiveCamera();","targetRectangle":{"y":150.32535791397095,"x":1236.93701171875,"width":590.009765625,"height":33}},{"text":"  obj = new Points();","targetRectangle":{"y":183.32535791397095,"x":1236.93701171875,"width":354.005859375,"height":33}},{"text":"  light = new HemisphereLight();","targetRectangle":{"y":216.32535791397095,"x":1236.93701171875,"width":539.4375,"height":33}},{"text":"  renderer = new WebGLRenderer();","targetRectangle":{"y":249.32535791397095,"x":1236.93701171875,"width":556.294921875,"height":33}},{"text":"}","targetRectangle":{"y":282.32535791397095,"x":1236.93701171875,"width":16.857421875,"height":33}},{"text":"Scene","targetRectangle":{"y":231.34514379501343,"x":112.12943410873413,"width":101.33999999999997,"height":51.398402881241054}},{"text":"Objects","targetRectangle":{"y":282.74354667625448,"x":112.12943410873413,"width":124.70400000000001,"height":81.398402881241054}},{"text":"Camera","targetRectangle":{"y":364.14194955749554,"x":112.12943410873413,"width":126.68399999999997,"height":81.398402881241054}},{"text":"Lights","targetRectangle":{"y":445.54035243873659,"x":112.12943410873413,"width":98.027999999999992,"height":81.398402881241054}},{"text":"Renderer","targetRectangle":{"y":526.93875531997764,"x":112.12943410873413,"width":147.34799999999996,"height":81.398402881241054}},{"text":"Program Structure","targetRectangle":{"y":86.967772603034973,"x":61.879581451416016,"width":354.15999999999997,"height":53.783973308556597}},{"text":"init();","targetRectangle":{"y":951.06493878364563,"x":1236.93701171875,"width":118.001953125,"height":33}},{"text":"animate();","targetRectangle":{"y":984.06493878364563,"x":1236.93701171875,"width":168.57421875,"height":33}},{"text":"destroy();","targetRectangle":{"y":1017.0649387836456,"x":1236.93701171875,"width":168.57421875,"height":33}},{"text":"function animate() {","targetRectangle":{"y":610.49627590179443,"x":1236.93701171875,"width":337.1484375,"height":33}},{"text":"  requestAnimationFrame(animate);","targetRectangle":{"y":643.49627590179443,"x":1236.93701171875,"width":556.294921875,"height":33}},{"text":"  update();","targetRectangle":{"y":676.49627590179443,"x":1236.93701171875,"width":185.431640625,"height":33}},{"text":"  render();","targetRectangle":{"y":709.49627590179443,"x":1236.93701171875,"width":185.431640625,"height":33}},{"text":"}","targetRectangle":{"y":742.49627590179443,"x":1236.93701171875,"width":16.857421875,"height":33}},{"text":"Create scene","targetRectangle":{"y":58.007289886474609,"x":878.07167529296873,"width":103.71199999999999,"height":75.10400390625}}],"baseLayer":{"animations":[],"initialState":{"affineTransform":[1,0,0,1,0,0],"masksToBounds":false,"rotation":0,"scale":1,"position":{"pointX":960,"pointY":540},"width":1920,"sublayerTransform":[1,0,0,0,0,1,0,0,0,0,1,0,0,0,0,1],"contentsRect":{"y":0,"x":0,"width":1,"height":1},"opacity":1,"edgeAntialiasingMask":251658240,"height":1080,"hidden":false,"anchorPoint":{"pointX":0.5,"pointY":0.5}},"objectID":"0","layers":[{"animations":[],"initialState":{"affineTransform":[1,0,0,1,0,0],"masksToBounds":false,"rotation":0,"scale":1,"position":{"pointX":960,"pointY":540},"width":1920,"sublayerTransform":[1,0,0,0,0,1,0,0,0,0,1,-0.00035007912466775983,0,0,0,1],"contentsRect":{"y":0,"x":0,"width":1,"height":1},"opacity":1,"edgeAntialiasingMask":251658240,"height":1080,"hidden":false,"anchorPoint":{"pointX":0.5,"pointY":0.5}},"layers":[{"animations":[],"layers":[],"texturedRectangle":{"isBackgroundTexture":false,"singleTextureOpacity":1,"textureType":0,"textBaseline":0,"textXHeight":0,"isVerticalText":false},"initialState":{"affineTransform":[1,0,0,1,0,0],"masksToBounds":false,"rotation":0,"scale":1,"position":{"pointX":960,"pointY":540},"width":1920,"sublayerTransform":[1,0,0,0,0,1,0,0,0,0,1,0,0,0,0,1],"contentsRect":{"y":0,"x":0,"width":1,"height":1},"opacity":1,"edgeAntialiasingMask":0,"height":1080,"hidden":false,"anchorPoint":{"pointX":0.5,"pointY":0.5}},"texture":"C054A79B4EE8BE1C7852CE41F3B9DE1D"}]}]}}]}